ont_fast5_api/__init__.py
ont_fast5_api/compression_settings.py
ont_fast5_api/data_sanitisation.py
ont_fast5_api/fast5_file.py
ont_fast5_api/fast5_info.py
ont_fast5_api/fast5_interface.py
ont_fast5_api/fast5_read.py
ont_fast5_api/helpers.py
ont_fast5_api/multi_fast5.py
ont_fast5_api/static_data.py
ont_fast5_api/analysis_tools/__init__.py
ont_fast5_api/analysis_tools/alignment.py
ont_fast5_api/analysis_tools/base_tool.py
ont_fast5_api/analysis_tools/basecall_1d.py
ont_fast5_api/analysis_tools/basecall_2d.py
ont_fast5_api/analysis_tools/event_detection.py
ont_fast5_api/analysis_tools/segmentation.py
ont_fast5_api/conversion_tools/__init__.py
ont_fast5_api/conversion_tools/check_file_compression.py
ont_fast5_api/conversion_tools/compress_fast5.py
ont_fast5_api/conversion_tools/conversion_utils.py
ont_fast5_api/conversion_tools/demux_fast5.py
ont_fast5_api/conversion_tools/fast5_subset.py
ont_fast5_api/conversion_tools/multi_to_single_fast5.py
ont_fast5_api/conversion_tools/single_to_multi_fast5.py
ont_fast5_api/vbz_plugin/libvbz_hdf_plugin.dylib
ont_fast5_api/vbz_plugin/libvbz_hdf_plugin_aarch64.so
ont_fast5_api/vbz_plugin/libvbz_hdf_plugin_m1.dylib
ont_fast5_api/vbz_plugin/libvbz_hdf_plugin_x86_64.so
ont_fast5_api/vbz_plugin/vbz_hdf_plugin.dll
test/__init__.py
test/helpers.py
test/test_alignment_tools.py
test/test_basecall_1d_tools.py
test/test_basecall_2d_tools.py
test/test_check_compression.py
test/test_compress_fast5.py
test/test_compression_settings.py
test/test_data_sanitisation.py
test/test_demux_fast5.py
test/test_event_detection_tools.py
test/test_fast5_conversion_utils.py
test/test_fast5_converter.py
test/test_fast5_file.py
test/test_fast5_interface.py
test/test_fast5_subset.py
test/test_hardlink_metadata.py
test/test_multi_fast5.py
test/test_segmentation_tools.py
ont_fast5_api-4.1.3.dist-info/LICENSE.md
ont_fast5_api-4.1.3.dist-info/METADATA
ont_fast5_api-4.1.3.dist-info/WHEEL
ont_fast5_api-4.1.3.dist-info/entry_points.txt
ont_fast5_api-4.1.3.dist-info/top_level.txt
ont_fast5_api-4.1.3.dist-info/RECORD
