Metadata-Version: 2.1
Name: ont-fast5-api
Version: 4.1.3
Summary: Oxford Nanopore Technologies fast5 API software
Home-page: https://github.com/nanoporetech/ont_fast5_api
Author: Oxford Nanopore Technologies, Limited
License: MPL 2.0
Keywords: fast5 nanopore
Classifier: Development Status :: 5 - Production/Stable
Classifier: Environment :: Console
Classifier: Intended Audience :: Developers
Classifier: Intended Audience :: Science/Research
Classifier: License :: OSI Approved :: Mozilla Public License 2.0 (MPL 2.0)
Classifier: Natural Language :: English
Classifier: Operating System :: Microsoft :: Windows
Classifier: Operating System :: POSIX :: Linux
Classifier: Operating System :: MacOS
Classifier: Programming Language :: Python :: 3 :: Only
Classifier: Topic :: Scientific/Engineering :: Bio-Informatics
Requires-Python: >=3.7
License-File: LICENSE.md
Requires-Dist: h5py >=3
Requires-Dist: numpy >=1.16
Requires-Dist: packaging
Requires-Dist: progressbar33 >=2.3.1
Requires-Dist: setuptools
